spectrum_plot/__init__.py
spectrum_plot/plotting.py
spectrum_plot-0.2.0.dist-info/LICENSE
spectrum_plot-0.2.0.dist-info/METADATA
spectrum_plot-0.2.0.dist-info/WHEEL
spectrum_plot-0.2.0.dist-info/top_level.txt
spectrum_plot-0.2.0.dist-info/RECORD
