Metadata-Version: 2.1
Name: spectrum-plot
Version: 0.2.0
Summary: Interactive spectrum plot. Update FFT plot on every new sampled data
Home-page: https://github.com/lisrael1/spectrum_plot
Author: Lior Israeli
Author-email: israelilior@gmail.com
Project-URL: Bug Tracker, https://github.com/lisrael1/spectrum_plot/issues
Classifier: Programming Language :: Python :: 3
Classifier: License :: OSI Approved :: MIT License
Classifier: Operating System :: OS Independent
Requires-Python: >=3.6
License-File: LICENSE
Requires-Dist: matplotlib
Requires-Dist: freq-note-converter
